quantumcat/__init__.py
quantumcat/main.py
quantumcat/algorithms/__init__.py
quantumcat/algorithms/grovers_algorithm.py
quantumcat/applications/__init__.py
quantumcat/applications/generator/__init__.py
quantumcat/applications/generator/otp.py
quantumcat/applications/generator/password.py
quantumcat/applications/generator/random_number.py
quantumcat/circuit/__init__.py
quantumcat/circuit/circuit.py
quantumcat/circuit/convert.py
quantumcat/circuit/execute_circuit.py
quantumcat/circuit/op_type.py
quantumcat/exceptions/__init__.py
quantumcat/exceptions/api_error.py
quantumcat/exceptions/circuit_error.py
quantumcat/exceptions/exception.py
quantumcat/exceptions/install_error.py
quantumcat/exceptions/otp_length.py
quantumcat/exceptions/password_length.py
quantumcat/gates/__init__.py
quantumcat/gates/custom_gates/__init__.py
quantumcat/gates/custom_gates/braket/__init__.py
quantumcat/gates/custom_gates/braket/ch_gate.py
quantumcat/gates/custom_gates/braket/crx_gate.py
quantumcat/gates/custom_gates/braket/cry_gate.py
quantumcat/gates/custom_gates/braket/crz_gate.py
quantumcat/gates/custom_gates/braket/csx_gate.py
quantumcat/gates/custom_gates/braket/cu1_gate.py
quantumcat/gates/custom_gates/braket/cu3_gate.py
quantumcat/gates/custom_gates/braket/cu_gate.py
quantumcat/gates/custom_gates/braket/dcx_gate.py
quantumcat/gates/custom_gates/braket/r_gate.py
quantumcat/gates/custom_gates/braket/rc3x_gate.py
quantumcat/gates/custom_gates/braket/rccx_gate.py
quantumcat/gates/custom_gates/braket/rzx_gate.py
quantumcat/gates/custom_gates/braket/u1_gate.py
quantumcat/gates/custom_gates/braket/u2_gate.py
quantumcat/gates/custom_gates/braket/u3_gate.py
quantumcat/gates/custom_gates/braket/u_gate.py
quantumcat/gates/custom_gates/cirq/__init__.py
quantumcat/gates/custom_gates/cirq/c3sx_gate.py
quantumcat/gates/custom_gates/cirq/c3x_gate.py
quantumcat/gates/custom_gates/cirq/c4x_gate.py
quantumcat/gates/custom_gates/cirq/ch_gate.py
quantumcat/gates/custom_gates/cirq/cphase_gate.py
quantumcat-0.1.8.dist-info/LICENSE.txt
quantumcat-0.1.8.dist-info/METADATA
quantumcat-0.1.8.dist-info/WHEEL
quantumcat-0.1.8.dist-info/top_level.txt
quantumcat-0.1.8.dist-info/RECORD
