Metadata-Version: 2.1
Name: quantumcat
Version: 0.1.8
Summary: A cross-platform, open-source, high-level quantum computing library
Home-page: https://quantumcat.io
Author: Artificial Brain Development Team
Author-email: entangled@artificialbrain.us
License: Apache-2.0
Project-URL: Bug Tracker, https://github.com/artificial-brain/quantumcat/issues
Project-URL: Documentation, https://github.com/artificial-brain/quantumcat
Project-URL: Source Code, https://github.com/artificial-brain/quantumcat
Keywords: quantum sdk
Platform: UNKNOWN
Requires-Python: >=3.8
License-File: LICENSE.txt
Requires-Dist: qiskit (==0.26.2)
Requires-Dist: cirq (==0.11.0)
Requires-Dist: amazon-braket-sdk (==1.6.4)
Requires-Dist: requests (==2.25.1)
Requires-Dist: seaborn (==0.11.1)
Requires-Dist: pylatexenc (==2.10)
